{
	"animations": [
		{
			"loop": false,
			"offsets": [
				39,
				125
			],
			"fps": 24,
			"anim": "idle",
			"indices": [],
			"name": "BF idle dance"
		},
		{
			"offsets": [
				28,
				93
			],
			"loop": false,
			"fps": 24,
			"anim": "singDOWN",
			"indices": [],
			"name": "BF NOTE DOWN"
		},
		{
			"offsets": [
				11,
				163
			],
			"loop": false,
			"fps": 24,
			"anim": "singUP",
			"indices": [],
			"name": "BF NOTE UP"
		},
		{
			"loop": false,
			"offsets": [
				348,
				121
			],
			"anim": "singLEFT",
			"fps": 24,
			"name": "BF NOTE RIGHT",
			"indices": []
		},
		{
			"loop": false,
			"offsets": [
				28,
				119
			],
			"anim": "singRIGHT",
			"fps": 24,
			"name": "BF NOTE LEFT",
			"indices": []
		}
	],
	"no_antialiasing": false,
	"image": "characters/New beeefers",
	"position": [
		40,
		400
	],
	"healthicon": "bf-4-2",
	"flip_x": true,
	"healthbar_colors": [
		49,
		176,
		209
	],
	"camera_position": [
		0,
		-110
	],
	"sing_duration": 4,
	"scale": 1
}