<?xml version="1.0" encoding="utf-8"?>
<TextureAtlas imagePath="bf-eye.png">
	<!-- Created with Adobe Animate version 22.0.3.179 -->
	<!-- http://www.adobe.com/products/animate.html -->
	<SubTexture name="BF NOTE DOWN0000" x="0" y="0" width="467" height="443"/>
	<SubTexture name="BF NOTE DOWN0001" x="467" y="0" width="467" height="443"/>
	<SubTexture name="BF NOTE DOWN0002" x="934" y="0" width="467" height="443"/>
	<SubTexture name="BF NOTE DOWN0003" x="1401" y="0" width="467" height="443"/>
	<SubTexture name="BF NOTE DOWN0004" x="1868" y="0" width="467" height="443"/>
	<SubTexture name="BF NOTE DOWN0005" x="2335" y="0" width="467" height="443"/>
	<SubTexture name="BF NOTE DOWN0006" x="2802" y="0" width="467" height="443"/>
	<SubTexture name="BF NOTE DOWN0007" x="3269" y="0" width="467" height="443"/>
	<SubTexture name="BF NOTE DOWN0008" x="3736" y="0" width="467" height="443"/>
	<SubTexture name="BF NOTE DOWN0009" x="4203" y="0" width="467" height="443"/>
	<SubTexture name="BF NOTE DOWN0010" x="4670" y="0" width="467" height="443"/>
	<SubTexture name="BF NOTE DOWN0011" x="5137" y="0" width="467" height="443"/>
	<SubTexture name="BF NOTE DOWN0012" x="5604" y="0" width="467" height="443"/>
	<SubTexture name="BF NOTE DOWN0013" x="6071" y="0" width="467" height="443"/>
	<SubTexture name="BF NOTE DOWN0014" x="6538" y="0" width="467" height="443"/>
	<SubTexture name="BF NOTE DOWN0015" x="7005" y="0" width="467" height="443"/>
	<SubTexture name="BF NOTE DOWN0016" x="7472" y="0" width="467" height="443"/>
	<SubTexture name="BF NOTE DOWN0017" x="0" y="443" width="467" height="443"/>
	<SubTexture name="BF NOTE DOWN0018" x="467" y="443" width="467" height="443"/>
	<SubTexture name="BF NOTE DOWN0019" x="934" y="443" width="467" height="443"/>
	<SubTexture name="BF NOTE DOWN0020" x="1401" y="443" width="467" height="443"/>
	<SubTexture name="BF NOTE DOWN0021" x="1868" y="443" width="467" height="443"/>
	<SubTexture name="BF NOTE DOWN0022" x="2335" y="443" width="467" height="443"/>
	<SubTexture name="BF NOTE DOWN0023" x="2802" y="443" width="467" height="443"/>
	<SubTexture name="BF NOTE DOWN0024" x="3269" y="443" width="467" height="443"/>
	<SubTexture name="BF NOTE DOWN0025" x="3736" y="443" width="467" height="443"/>
	<SubTexture name="BF NOTE DOWN0026" x="4203" y="443" width="467" height="443"/>
	<SubTexture name="BF NOTE DOWN0027" x="4670" y="443" width="467" height="443"/>
	<SubTexture name="BF NOTE DOWN0028" x="5137" y="443" width="467" height="443"/>
	<SubTexture name="BF NOTE DOWN0029" x="5604" y="443" width="467" height="443"/>
	<SubTexture name="BF NOTE LEFT0000" x="6071" y="443" width="763" height="463"/>
	<SubTexture name="BF NOTE LEFT0001" x="6834" y="443" width="763" height="463"/>
	<SubTexture name="BF NOTE LEFT0002" x="0" y="906" width="763" height="463"/>
	<SubTexture name="BF NOTE LEFT0003" x="763" y="906" width="763" height="463"/>
	<SubTexture name="BF NOTE LEFT0004" x="1526" y="906" width="763" height="463"/>
	<SubTexture name="BF NOTE LEFT0005" x="2289" y="906" width="763" height="463"/>
	<SubTexture name="BF NOTE LEFT0006" x="3052" y="906" width="763" height="463"/>
	<SubTexture name="BF NOTE LEFT0007" x="3815" y="906" width="763" height="463"/>
	<SubTexture name="BF NOTE LEFT0008" x="4578" y="906" width="763" height="463"/>
	<SubTexture name="BF NOTE LEFT0009" x="5341" y="906" width="763" height="463"/>
	<SubTexture name="BF NOTE LEFT0010" x="6104" y="906" width="763" height="463"/>
	<SubTexture name="BF NOTE LEFT0011" x="6867" y="906" width="763" height="463"/>
	<SubTexture name="BF NOTE LEFT0012" x="0" y="1369" width="763" height="463"/>
	<SubTexture name="BF NOTE LEFT0013" x="763" y="1369" width="763" height="463"/>
	<SubTexture name="BF NOTE LEFT0014" x="1526" y="1369" width="763" height="463"/>
	<SubTexture name="BF NOTE RIGHT0000" x="2289" y="1369" width="837" height="463"/>
	<SubTexture name="BF NOTE RIGHT0001" x="3126" y="1369" width="837" height="463"/>
	<SubTexture name="BF NOTE RIGHT0002" x="3963" y="1369" width="837" height="463"/>
	<SubTexture name="BF NOTE RIGHT0003" x="4800" y="1369" width="837" height="463"/>
	<SubTexture name="BF NOTE RIGHT0004" x="5637" y="1369" width="837" height="463"/>
	<SubTexture name="BF NOTE RIGHT0005" x="6474" y="1369" width="837" height="463"/>
	<SubTexture name="BF NOTE RIGHT0006" x="7311" y="1369" width="837" height="463"/>
	<SubTexture name="BF NOTE RIGHT0007" x="0" y="1832" width="837" height="463"/>
	<SubTexture name="BF NOTE RIGHT0008" x="837" y="1832" width="837" height="463"/>
	<SubTexture name="BF NOTE RIGHT0009" x="1674" y="1832" width="837" height="463"/>
	<SubTexture name="BF NOTE RIGHT0010" x="2511" y="1832" width="837" height="463"/>
	<SubTexture name="BF NOTE RIGHT0011" x="3348" y="1832" width="837" height="463"/>
	<SubTexture name="BF NOTE RIGHT0012" x="4185" y="1832" width="837" height="463"/>
	<SubTexture name="BF NOTE RIGHT0013" x="5022" y="1832" width="837" height="463"/>
	<SubTexture name="BF NOTE RIGHT0014" x="5859" y="1832" width="837" height="463"/>
	<SubTexture name="BF NOTE RIGHT0015" x="6696" y="1832" width="837" height="463"/>
	<SubTexture name="BF NOTE RIGHT0016" x="0" y="2295" width="837" height="463"/>
	<SubTexture name="BF NOTE RIGHT0017" x="837" y="2295" width="837" height="463"/>
	<SubTexture name="BF NOTE RIGHT0018" x="1674" y="2295" width="837" height="463"/>
	<SubTexture name="BF NOTE RIGHT0019" x="2511" y="2295" width="837" height="463"/>
	<SubTexture name="BF NOTE RIGHT0020" x="3348" y="2295" width="837" height="463"/>
	<SubTexture name="BF NOTE RIGHT0021" x="4185" y="2295" width="837" height="463"/>
	<SubTexture name="BF NOTE RIGHT0022" x="5022" y="2295" width="837" height="463"/>
	<SubTexture name="BF NOTE RIGHT0023" x="5859" y="2295" width="837" height="463"/>
	<SubTexture name="BF NOTE RIGHT0024" x="6696" y="2295" width="837" height="463"/>
	<SubTexture name="BF NOTE RIGHT0025" x="0" y="2758" width="837" height="463"/>
	<SubTexture name="BF NOTE RIGHT0026" x="837" y="2758" width="837" height="463"/>
	<SubTexture name="BF NOTE RIGHT0027" x="1674" y="2758" width="837" height="463"/>
	<SubTexture name="BF NOTE RIGHT0028" x="2511" y="2758" width="837" height="463"/>
	<SubTexture name="BF NOTE RIGHT0029" x="3348" y="2758" width="837" height="463"/>
	<SubTexture name="BF NOTE RIGHT0030" x="4185" y="2758" width="837" height="463"/>
	<SubTexture name="BF NOTE RIGHT0031" x="5022" y="2758" width="837" height="463"/>
	<SubTexture name="BF NOTE RIGHT0032" x="5859" y="2758" width="837" height="463"/>
	<SubTexture name="BF NOTE RIGHT0033" x="6696" y="2758" width="837" height="463"/>
	<SubTexture name="BF NOTE RIGHT0034" x="0" y="3221" width="837" height="463"/>
	<SubTexture name="BF NOTE RIGHT0035" x="837" y="3221" width="837" height="463"/>
	<SubTexture name="BF NOTE RIGHT0036" x="1674" y="3221" width="837" height="463"/>
	<SubTexture name="BF NOTE RIGHT0037" x="2511" y="3221" width="837" height="463"/>
	<SubTexture name="BF NOTE RIGHT0038" x="3348" y="3221" width="837" height="463"/>
	<SubTexture name="BF NOTE UP0000" x="4185" y="3221" width="494" height="528"/>
	<SubTexture name="BF NOTE UP0001" x="4679" y="3221" width="494" height="528"/>
	<SubTexture name="BF NOTE UP0002" x="5173" y="3221" width="494" height="528"/>
	<SubTexture name="BF NOTE UP0003" x="5667" y="3221" width="494" height="528"/>
	<SubTexture name="BF NOTE UP0004" x="6161" y="3221" width="494" height="528"/>
	<SubTexture name="BF NOTE UP0005" x="6655" y="3221" width="494" height="528"/>
	<SubTexture name="BF NOTE UP0006" x="7149" y="3221" width="494" height="528"/>
	<SubTexture name="BF NOTE UP0007" x="7643" y="3221" width="494" height="528"/>
	<SubTexture name="BF NOTE UP0008" x="0" y="3749" width="494" height="528"/>
	<SubTexture name="BF NOTE UP0009" x="494" y="3749" width="494" height="528"/>
	<SubTexture name="BF NOTE UP0010" x="988" y="3749" width="494" height="528"/>
	<SubTexture name="BF NOTE UP0011" x="1482" y="3749" width="494" height="528"/>
	<SubTexture name="BF NOTE UP0012" x="1976" y="3749" width="494" height="528"/>
	<SubTexture name="BF NOTE UP0013" x="2470" y="3749" width="494" height="528"/>
	<SubTexture name="BF NOTE UP0014" x="2964" y="3749" width="494" height="528"/>
	<SubTexture name="BF idle dance0000" x="3458" y="3749" width="792" height="469"/>
	<SubTexture name="BF idle dance0001" x="4250" y="3749" width="792" height="469"/>
	<SubTexture name="BF idle dance0002" x="5042" y="3749" width="792" height="469"/>
	<SubTexture name="BF idle dance0003" x="5834" y="3749" width="792" height="469"/>
	<SubTexture name="BF idle dance0004" x="6626" y="3749" width="792" height="469"/>
	<SubTexture name="BF idle dance0005" x="0" y="4277" width="792" height="469"/>
	<SubTexture name="BF idle dance0006" x="792" y="4277" width="792" height="469"/>
	<SubTexture name="BF idle dance0007" x="1584" y="4277" width="792" height="469"/>
	<SubTexture name="BF idle dance0008" x="2376" y="4277" width="792" height="469"/>
	<SubTexture name="BF idle dance0009" x="3168" y="4277" width="792" height="469"/>
	<SubTexture name="BF idle dance0010" x="3960" y="4277" width="792" height="469"/>
	<SubTexture name="BF idle dance0011" x="4752" y="4277" width="792" height="469"/>
	<SubTexture name="BF idle dance0012" x="5544" y="4277" width="792" height="469"/>
	<SubTexture name="BF idle dance0013" x="6336" y="4277" width="792" height="469"/>
</TextureAtlas>
